dnv/__init__.py
dnv/oneworkflow/__init__.py
dnv/oneworkflow/_user_agreement_manager.py
dnv/oneworkflow/composite_executable_command.py
dnv/oneworkflow/config.py
dnv/oneworkflow/container_execution_workunit.py
dnv/oneworkflow/create_input_file_from_file_template_command.py
dnv/oneworkflow/create_input_file_from_inline_template_command.py
dnv/oneworkflow/create_input_file_from_template_command.py
dnv/oneworkflow/executable_command.py
dnv/oneworkflow/file_transfer_progress_monitor.py
dnv/oneworkflow/job_builder.py
dnv/oneworkflow/logging_utils.py
dnv/oneworkflow/oneworkflowclient.py
dnv/oneworkflow/package_manager.py
dnv/oneworkflow/python_command.py
dnv/oneworkflow/repository.py
dnv/oneworkflow/worker_command.py
dnv/oneworkflow/utils/__init__.py
dnv/oneworkflow/utils/_file_transfer_progress_indicator.py
dnv/oneworkflow/utils/_workflow_utils_private.py
dnv/oneworkflow/utils/command_info.py
dnv/oneworkflow/utils/job_result.py
dnv/oneworkflow/utils/one_workflow_client_builder.py
dnv/oneworkflow/utils/platform.py
dnv/oneworkflow/utils/process_manager.py
dnv/oneworkflow/utils/workflow_commands_runners_parallel.py
dnv/oneworkflow/utils/workflow_commands_runners_sequential.py
dnv/oneworkflow/utils/workflow_runners.py
dnv/oneworkflow/utils/workflow_runners_managed.py
dnv/oneworkflow/utils/workflow_runtime_installer.py
dnv/oneworkflow/utils/workunit_extension.py
dnv_oneworkflow-1.1.2.dist-info/licenses/LICENSE
dnv_oneworkflow-1.1.2.dist-info/METADATA
dnv_oneworkflow-1.1.2.dist-info/WHEEL
dnv_oneworkflow-1.1.2.dist-info/top_level.txt
dnv_oneworkflow-1.1.2.dist-info/RECORD
