Metadata-Version: 2.4
Name: dnv-oneworkflow
Version: 1.1.2
Summary: Python library for developing and running workflows locally or on the OneCompute cloud platform
Author-email: DNV AS <software.support@dnv.com>
License: MIT License
Project-URL: Homepage, https://myworkspace.dnv.com/knowledge-centre/sesam-workflows/usermanual/?document=sesam-workflows-ow-overview
Keywords: onecompute,oneworkflow,workflow
Classifier: License :: OSI Approved :: MIT License
Classifier: Programming Language :: Python
Classifier: Programming Language :: Python :: 3.10
Requires-Python: >=3.10
License-File: LICENSE
Requires-Dist: dnv-onecompute
Requires-Dist: cryptography==44.0.1
Requires-Dist: ipywidgets==8.1.5
Requires-Dist: signify==0.5.2
Requires-Dist: tqdm==4.67.1
Dynamic: license-file
